halite_season_converter/__init__.py
halite_season_converter/converters/__init__.py
halite_season_converter/converters/convert_31_to_3.py
halite_season_converter/converters/convert_3_to_31.py
halite_season_converter/schemas/__init__.py
halite_season_converter/schemas/halite_2.py
halite_season_converter/schemas/halite_3.py
halite_season_converter/schemas/halite_31.py
halite_season_converter/utils.py
halite_season_converter-0.1.0.dist-info/LICENSE
halite_season_converter-0.1.0.dist-info/WHEEL
halite_season_converter-0.1.0.dist-info/METADATA
halite_season_converter-0.1.0.dist-info/RECORD
