Metadata-Version: 2.1
Name: halite-season-converter
Version: 0.1.0
Summary: Bidirectional converter for Halite season 2, 3 and 3.1.
License: MIT
Author: Jan-Benedikt Jagusch
Author-email: jan.jagusch@gmail.com
Requires-Python: >=3.7,<4.0
Classifier: License :: OSI Approved :: MIT License
Classifier: Programming Language :: Python :: 3
Classifier: Programming Language :: Python :: 3.7
Classifier: Programming Language :: Python :: 3.8
Requires-Dist: dataclasses-json (>=0.4.2,<0.5.0)
Requires-Dist: kaggle-environments (>=0.2.6,<0.3.0)
Requires-Dist: requests (>=2.23.0,<3.0.0)
Requires-Dist: zstd (>=1.4.4,<2.0.0)
